frankwolfetopython/__init__.py
frankwolfetopython/_julia_env.py
frankwolfetopython/frank_wolfe_model_wrapper.py
frankwolfetopython/frankwolfe.py
frankwolfetopython/moi_lmo_wrapper.py
frankwolfetopython/objective_function_wrapper.py
frankwolfetopython-0.3.2.dist-info/METADATA
frankwolfetopython-0.3.2.dist-info/WHEEL
frankwolfetopython-0.3.2.dist-info/top_level.txt
frankwolfetopython-0.3.2.dist-info/RECORD
