Metadata-Version: 2.1
Name: frankwolfetopython
Version: 0.3.2
Summary: A Python wrapper for the FrankWolfe.jl Julia package,         providing an interface for Frank-Wolfe optimization methods.
Author: Matthew Mione
Author-email: matthewmione@gmail.com
Requires-Dist: juliacall >=0.9.0
Requires-Dist: numpy >=1.20.0
